{
  "0": [
    {
      "object_id": 1,
      "object": "black gaming monitor",
      "position": "left side of the image",
      "image_id": 0
    },
    {
      "object_id": 2,
      "object": "black laptop with a logo",
      "position": "center of the image on the desk",
      "image_id": 0
    },
    {
      "object_id": 3,
      "object": "black keyboard",
      "position": "front of the laptop on the desk",
      "image_id": 0
    },
    {
      "object_id": 4,
      "object": "white wireless speaker",
      "position": "right side of the laptop on the desk",
      "image_id": 0
    },
    {
      "object_id": 5,
      "object": "silver thermos",
      "position": "right side of the speaker on the desk",
      "image_id": 0
    },
    {
      "object_id": 6,
      "object": "blue office chair",
      "position": "bottom right of the image",
      "image_id": 0
    },
    {
      "object_id": 7,
      "object": "various colored boxes and containers",
      "position": "background on the right side of the image",
      "image_id": 0
    },
    {
      "object_id": 8,
      "object": "multiple computer monitors",
      "position": "background on the left side of the image",
      "image_id": 0
    },
    {
      "object_id": 9,
      "object": "white mannequin head",
      "position": "background on the left side of the image",
      "image_id": 0
    },
    {
      "object_id": 10,
      "object": "cables and wires",
      "position": "on the floor near the chair",
      "image_id": 0
    }
  ]
}